{
  "db_name": "PostgreSQL",
  "query": "INSERT INTO game_bots (id, game_id, name, bot_name)\n         VALUES (uuid_generate_v4(), $1, $2, 'medium')\n         RETURNING id",
  "describe": {
    "columns": [
      {
        "ordinal": 0,
        "name": "id",
        "type_info": "Uuid"
      }
    ],
    "parameters": {
      "Left": [
        "Uuid",
        "Text"
      ]
    },
    "nullable": [
      false
    ]
  },
  "hash": "a693234bed685c7c4e5a4c3a2fd354c9a1e1f1d44ee12bdd2a08d023ae73ffb7"
}
